Workbook

Sheet Lisez-moi
A1: Le bookmaker gagne toujours. Même au MMA. · CORRIGÉ
A3: Corrigé : toutes les formules sont en place, et chaque graphique a son onglet (G1 à G5). Ce sont ces graphiques qui sont sur le site.
A5: Les onglets
A6: • Argent : mises, gains redistribués, part gardée par les opérateurs (ARJEL / ANJ, 2010-2025).
A7: • Evenements : nombre d'événements UFC par année (ufcstats.com).
A8: • Calibration : probabilité annoncée par la cote vs taux de victoire réel.
A9: • Rendement : ce que rapporte 1 € misé, par tranche de cote.
A10: • Simulateur : un parieur, 100 paris sur de vrais combats tirés au hasard (F9 = nouveau parieur).
A11: • Combats : les 6 916 combats (cotes décimales, vainqueur) utilisés par le simulateur.
A13: Sources : Ultimate UFC Dataset (github.com/shortlikeafox/ultimate_ufc_dataset), ufcstats.com, rapports ARJEL et ANJ.

Sheet Argent
A1: Paris sportifs en ligne en France (millions d'euros)
A2: Sources : ARJEL (2010-2018), ANJ (2020-2025). 2019 : mises déduites de la hausse publiée en 2020. 2024 : chiffre révisé par l'ANJ.
A4: Année | B4: Mises (M€) | C4: Gardé par les opérateurs (M€) | D4: Revenu aux parieurs (M€) | E4: Part gardée | F4: Revenu (Md€) | G4: Gardé (Md€)
A5: 2010 | B5: 448 | C5: 79 | D5: =B5-C5 -> 369 | E5: =IFERROR(C5/B5,0) -> 0.17633929 | F5: =D5/1000 -> 0.369 | G5: =C5/1000 -> 0.079
A6: 2011 | B6: 592 | C6: 115 | D6: =B6-C6 -> 477 | E6: =IFERROR(C6/B6,0) -> 0.19425676 | F6: =D6/1000 -> 0.477 | G6: =C6/1000 -> 0.115
A7: 2012 | B7: 705 | C7: 138 | D7: =B7-C7 -> 567 | E7: =IFERROR(C7/B7,0) -> 0.19574468 | F7: =D7/1000 -> 0.567 | G7: =C7/1000 -> 0.138
A8: 2013 | B8: 848 | C8: 164 | D8: =B8-C8 -> 684 | E8: =IFERROR(C8/B8,0) -> 0.19339623 | F8: =D8/1000 -> 0.684 | G8: =C8/1000 -> 0.164
A9: 2014 | B9: 1109 | C9: 228 | D9: =B9-C9 -> 881 | E9: =IFERROR(C9/B9,0) -> 0.20559062 | F9: =D9/1000 -> 0.881 | G9: =C9/1000 -> 0.228
A10: 2015 | B10: 1440 | C10: 270 | D10: =B10-C10 -> 1170 | E10: =IFERROR(C10/B10,0) -> 0.1875 | F10: =D10/1000 -> 1.17 | G10: =C10/1000 -> 0.27
A11: 2016 | B11: 2081 | C11: 349 | D11: =B11-C11 -> 1732 | E11: =IFERROR(C11/B11,0) -> 0.16770783 | F11: =D11/1000 -> 1.732 | G11: =C11/1000 -> 0.349
A12: 2017 | B12: 2510 | C12: 472 | D12: =B12-C12 -> 2038 | E12: =IFERROR(C12/B12,0) -> 0.18804781 | F12: =D12/1000 -> 2.038 | G12: =C12/1000 -> 0.472
A13: 2018 | B13: 3904 | C13: 691 | D13: =B13-C13 -> 3213 | E13: =IFERROR(C13/B13,0) -> 0.17699795 | F13: =D13/1000 -> 3.213 | G13: =C13/1000 -> 0.691
A14: 2019 | B14: 5049 | C14: 880 | D14: =B14-C14 -> 4169 | E14: =IFERROR(C14/B14,0) -> 0.17429194 | F14: =D14/1000 -> 4.169 | G14: =C14/1000 -> 0.88
A15: 2020 | B15: 5352 | C15: 940 | D15: =B15-C15 -> 4412 | E15: =IFERROR(C15/B15,0) -> 0.17563528 | F15: =D15/1000 -> 4.412 | G15: =C15/1000 -> 0.94
A16: 2021 | B16: 7890 | C16: 1360 | D16: =B16-C16 -> 6530 | E16: =IFERROR(C16/B16,0) -> 0.17237009 | F16: =D16/1000 -> 6.53 | G16: =C16/1000 -> 1.36
... A20: 2025 | B20: 11517 | C20: 1766 | D20: =B20-C20 -> 9751 | E20: =IFERROR(C20/B20,0) -> 0.15333854 | F20: =D20/1000 -> 9.751 | G20: =C20/1000 -> 1.766
A21: Total | B21: =SUM(B5:B20) -> 70517 | C21: =SUM(C5:C20) -> 11908 | D21: =SUM(D5:D20) -> 58609 | E21: =C21/B21 -> 0.16886708
A23: Corrélation mises / gardé : | E23: =CORREL(B5:B20,C5:C20) -> 0.99660121

Sheet Simulateur
A1: Simulateur : un parieur, 100 paris, touche F9 pour relancer
A2: Chaque ligne tire un vrai combat au hasard (onglet Combats), choisit un camp au hasard et applique la vraie cote et le vrai résultat.
A4: Mise par pari (€) : | C4: 10 | E4: Bilan final : | F4: =H106 -> 65.7
A5: Pari n° | B5: Ligne du combat | C5: Camp | D5: Cote | E5: Gagné ? | F5: Gain (€) | H5: Cagnotte (€)
A6: 0 | H6: 0
A7: 1 | B7: =RANDBETWEEN(5,6920) -> 3343 | C7: =IF(RAND()<0.5,"rouge","bleu") -> bleu | D7: =IF(C7="rouge",INDEX(Combats!A:A,B7),INDEX(Combats!B:B,B7)) -> 4.6 | E7: =IF(C7="rouge",INDEX(Combats!C:C,B7)=1,INDEX(Combats!C:C,B7)=0) -> TRUE | F7: =IF(E7,$C$4*(D7-1),-$C$4) -> 36 | H7: =H6+F7 -> 36
A8: 2 | B8: =RANDBETWEEN(5,6920) -> 1811 | C8: =IF(RAND()<0.5,"rouge","bleu") -> bleu | D8: =IF(C8="rouge",INDEX(Combats!A:A,B8),INDEX(Combats!B:B,B8)) -> 1.29 | E8: =IF(C8="rouge",INDEX(Combats!C:C,B8)=1,INDEX(Combats!C:C,B8)=0) -> TRUE | F8: =IF(E8,$C$4*(D8-1),-$C$4) -> 2.9 | H8: =H7+F8 -> 38.9
A9: 3 | B9: =RANDBETWEEN(5,6920) -> 1197 | C9: =IF(RAND()<0.5,"rouge","bleu") -> rouge | D9: =IF(C9="rouge",INDEX(Combats!A:A,B9),INDEX(Combats!B:B,B9)) -> 1.53 | E9: =IF(C9="rouge",INDEX(Combats!C:C,B9)=1,INDEX(Combats!C:C,B9)=0) -> TRUE | F9: =IF(E9,$C$4*(D9-1),-$C$4) -> 5.3 | H9: =H8+F9 -> 44.2
A10: 4 | B10: =RANDBETWEEN(5,6920) -> 3531 | C10: =IF(RAND()<0.5,"rouge","bleu") -> bleu | D10: =IF(C10="rouge",INDEX(Combats!A:A,B10),INDEX(Combats!B:B,B10)) -> 1.59 | E10: =IF(C10="rouge",INDEX(Combats!C:C,B10)=1,INDEX(Combats!C:C,B10)=0) -> TRUE | F10: =IF(E10,$C$4*(D10-1),-$C$4) -> 5.9 | H10: =H9+F10 -> 50.1
A11: 5 | B11: =RANDBETWEEN(5,6920) -> 1895 | C11: =IF(RAND()<0.5,"rouge","bleu") -> bleu | D11: =IF(C11="rouge",INDEX(Combats!A:A,B11),INDEX(Combats!B:B,B11)) -> 2.2 | E11: =IF(C11="rouge",INDEX(Combats!C:C,B11)=1,INDEX(Combats!C:C,B11)=0) -> FALSE | F11: =IF(E11,$C$4*(D11-1),-$C$4) -> -10 | H11: =H10+F11 -> 40.1
A12: 6 | B12: =RANDBETWEEN(5,6920) -> 5321 | C12: =IF(RAND()<0.5,"rouge","bleu") -> rouge | D12: =IF(C12="rouge",INDEX(Combats!A:A,B12),INDEX(Combats!B:B,B12)) -> 1.62 | E12: =IF(C12="rouge",INDEX(Combats!C:C,B12)=1,INDEX(Combats!C:C,B12)=0) -> FALSE | F12: =IF(E12,$C$4*(D12-1),-$C$4) -> -10 | H12: =H11+F12 -> 30.1
A13: 7 | B13: =RANDBETWEEN(5,6920) -> 3704 | C13: =IF(RAND()<0.5,"rouge","bleu") -> bleu | D13: =IF(C13="rouge",INDEX(Combats!A:A,B13),INDEX(Combats!B:B,B13)) -> 1.38 | E13: =IF(C13="rouge",INDEX(Combats!C:C,B13)=1,INDEX(Combats!C:C,B13)=0) -> TRUE | F13: =IF(E13,$C$4*(D13-1),-$C$4) -> 3.8 | H13: =H12+F13 -> 33.9
A14: 8 | B14: =RANDBETWEEN(5,6920) -> 879 | C14: =IF(RAND()<0.5,"rouge","bleu") -> rouge | D14: =IF(C14="rouge",INDEX(Combats!A:A,B14),INDEX(Combats!B:B,B14)) -> 2.9 | E14: =IF(C14="rouge",INDEX(Combats!C:C,B14)=1,INDEX(Combats!C:C,B14)=0) -> FALSE | F14: =IF(E14,$C$4*(D14-1),-$C$4) -> -10 | H14: =H13+F14 -> 23.9
A15: 9 | B15: =RANDBETWEEN(5,6920) -> 937 | C15: =IF(RAND()<0.5,"rouge","bleu") -> rouge | D15: =IF(C15="rouge",INDEX(Combats!A:A,B15),INDEX(Combats!B:B,B15)) -> 1.07 | E15: =IF(C15="rouge",INDEX(Combats!C:C,B15)=1,INDEX(Combats!C:C,B15)=0) -> TRUE | F15: =IF(E15,$C$4*(D15-1),-$C$4) -> 0.7 | H15: =H14+F15 -> 24.6
A16: 10 | B16: =RANDBETWEEN(5,6920) -> 1868 | C16: =IF(RAND()<0.5,"rouge","bleu") -> bleu | D16: =IF(C16="rouge",INDEX(Combats!A:A,B16),INDEX(Combats!B:B,B16)) -> 2.35 | E16: =IF(C16="rouge",INDEX(Combats!C:C,B16)=1,INDEX(Combats!C:C,B16)=0) -> FALSE | F16: =IF(E16,$C$4*(D16-1),-$C$4) -> -10 | H16: =H15+F16 -> 14.6
A17: 11 | B17: =RANDBETWEEN(5,6920) -> 1641 | C17: =IF(RAND()<0.5,"rouge","bleu") -> rouge | D17: =IF(C17="rouge",INDEX(Combats!A:A,B17),INDEX(Combats!B:B,B17)) -> 2.8 | E17: =IF(C17="rouge",INDEX(Combats!C:C,B17)=1,INDEX(Combats!C:C,B17)=0) -> FALSE | F17: =IF(E17,$C$4*(D17-1),-$C$4) -> -10 | H17: =H16+F17 -> 4.6
A18: 12 | B18: =RANDBETWEEN(5,6920) -> 3135 | C18: =IF(RAND()<0.5,"rouge","bleu") -> rouge | D18: =IF(C18="rouge",INDEX(Combats!A:A,B18),INDEX(Combats!B:B,B18)) -> 4 | E18: =IF(C18="rouge",INDEX(Combats!C:C,B18)=1,INDEX(Combats!C:C,B18)=0) -> FALSE | F18: =IF(E18,$C$4*(D18-1),-$C$4) -> -10 | H18: =H17+F18 -> -5.4
... A106: 100 | B106: =RANDBETWEEN(5,6920) -> 596 | C106: =IF(RAND()<0.5,"rouge","bleu") -> rouge | D106: =IF(C106="rouge",INDEX(Combats!A:A,B106),INDEX(Combats!B:B,B106)) -> 1.08 | E106: =IF(C106="rouge",INDEX(Combats!C:C,B106)=1,INDEX(Combats!C:C,B106)=0) -> FALSE | F106: =IF(E106,$C$4*(D106-1),-$C$4) -> -10 | H106: =H105+F106 -> 65.7

Sheet G1 Argent

Sheet Evenements
A1: Événements UFC organisés chaque année
A2: Source : ufcstats.com
A4: Année | B4: Événements
A5: 2001 | B5: 5
A6: 2002 | B6: 7
A7: 2003 | B7: 5
A8: 2004 | B8: 5
A9: 2005 | B9: 10
A10: 2006 | B10: 18
A11: 2007 | B11: 19
A12: 2008 | B12: 20
A13: 2009 | B13: 20
A14: 2010 | B14: 24
A15: 2011 | B15: 27
A16: 2012 | B16: 31
... A29: 2025 | B29: 42

Sheet G2 Evenements

Sheet Calibration
A1: Probabilité annoncée par la cote vs taux de victoire réel
A2: Source : Ultimate UFC Dataset, 2010-2026. Marge du bookmaker retirée.
A4: Probabilité annoncée | B4: Taux de victoire réel | C4: Combattants | D4: Cote parfaite
A5: 0.163 | B5: 0.128 | C5: 602 | D5: =A5 -> 0.163
A6: 0.254 | B6: 0.22 | C6: 1621 | D6: =A6 -> 0.254
A7: 0.351 | B7: 0.354 | C7: 2346 | D7: =A7 -> 0.351
A8: 0.449 | B8: 0.461 | C8: 2447 | D8: =A8 -> 0.449
A9: 0.557 | B9: 0.543 | C9: 2207 | D9: =A9 -> 0.557
A10: 0.649 | B10: 0.646 | C10: 2346 | D10: =A10 -> 0.649
A11: 0.746 | B11: 0.779 | C11: 1627 | D11: =A11 -> 0.746
A12: 0.837 | B12: 0.876 | C12: 596 | D12: =A12 -> 0.837

Sheet G3 Calibration

Sheet Rendement
A1: Rendement moyen d'un pari, par tranche de cote
A2: Source : Ultimate UFC Dataset. Rendement = gains / mises − 1, en misant 1 € sur chaque combattant de la tranche.
A4: Tranche de cote | B4: Rendement moyen | C4: Marge d'erreur (95 %) | D4: Taux de victoire | E4: Paris
A5: < 1,30 | B5: 0.016 | C5: 0.023 | D5: 0.842 | E5: 1422
A6: 1,30-1,60 | B6: -0.026 | C6: 0.024 | D6: 0.677 | E6: 3026
A7: 1,60-2 | B7: -0.052 | C7: 0.032 | D7: 0.536 | E7: 2970
A8: 2-3 | B8: -0.021 | C8: 0.039 | D8: 0.401 | E8: 3774
A9: 3-5 | B9: -0.125 | C9: 0.067 | D9: 0.241 | E9: 2090
A10: > 5 | B10: -0.304 | C10: 0.164 | D10: 0.115 | E10: 550

Sheet G4 Rendement

Sheet Calculatrice
A1: Calculatrice : la marge cachée dans deux cotes
A2: Changez les deux cotes jaunes : tout le reste se recalcule.
A4: Cote du combattant A | B4: 1.77
A5: Cote du combattant B | B5: 2.02
A7: Probabilité annoncée pour A | B7: =1/B4 -> 0.56497175
A8: Probabilité annoncée pour B | B8: =1/B5 -> 0.4950495
A9: Total des deux probabilités | B9: =B7+B8 -> 1.0600213
A10: Marge du bookmaker | B10: =B9-1 -> 0.060021256
A11: Sur 100 € misés, le bookmaker garde (€) | B11: =100*B10/B9 -> 5.6622691
A13: Exemple : Adesanya vs Pyfer, mars 2026 (cotes américaines −130 / +102).

Sheet Combats
A1: Les combats UFC et leurs cotes (décimales)
A2: Source : Ultimate UFC Dataset, 2010-2026.
A4: Cote rouge | B4: Cote bleu | C4: Rouge gagne (1 = oui) | D4: Année
A5: 1.77 | B5: 2.02 | C5: 0 | D5: 2026
A6: 2.24 | B6: 1.63 | C6: 1 | D6: 2026
A7: 1.11 | B7: 6.5 | C7: 1 | D7: 2026
A8: 3.35 | B8: 1.31 | C8: 0 | D8: 2026
A9: 1.63 | B9: 2.24 | C9: 0 | D9: 2026
A10: 1.67 | B10: 2.18 | C10: 1 | D10: 2026
A11: 1.34 | B11: 3.2 | C11: 0 | D11: 2026
A12: 1.36 | B12: 3.1 | C12: 0 | D12: 2026
A13: 1.96 | B13: 1.82 | C13: 0 | D13: 2026
A14: 1.88 | B14: 1.88 | C14: 1 | D14: 2026
A15: 1.23 | B15: 4.1 | C15: 1 | D15: 2026
A16: 1.21 | B16: 4.3 | C16: 1 | D16: 2026
... A6920: 2.4 | B6920: 1.62 | C6920: 0 | D6920: 2010

Sheet G5 Simulateur

Sheet Paris
A1: Tous les paris possibles (les deux camps de chaque combat)
A2: Gain = ce que rapporte un pari de 10 € : 10 × (cote − 1) s'il gagne, −10 sinon.
A4: Cote | B4: Gagné (1 = oui) | C4: Gain pour 10 € (€)
A5: 1.77 | B5: 0 | C5: =IF(B5=1,10*(A5-1),-10) -> -10
A6: 2.24 | B6: 1 | C6: =IF(B6=1,10*(A6-1),-10) -> 12.4
A7: 1.11 | B7: 1 | C7: =IF(B7=1,10*(A7-1),-10) -> 1.1
A8: 3.35 | B8: 0 | C8: =IF(B8=1,10*(A8-1),-10) -> -10
A9: 1.63 | B9: 0 | C9: =IF(B9=1,10*(A9-1),-10) -> -10
A10: 1.67 | B10: 1 | C10: =IF(B10=1,10*(A10-1),-10) -> 6.7
A11: 1.34 | B11: 0 | C11: =IF(B11=1,10*(A11-1),-10) -> -10
A12: 1.36 | B12: 0 | C12: =IF(B12=1,10*(A12-1),-10) -> -10
A13: 1.96 | B13: 0 | C13: =IF(B13=1,10*(A13-1),-10) -> -10
A14: 1.88 | B14: 1 | C14: =IF(B14=1,10*(A14-1),-10) -> 8.8
A15: 1.23 | B15: 1 | C15: =IF(B15=1,10*(A15-1),-10) -> 2.3
A16: 1.21 | B16: 1 | C16: =IF(B16=1,10*(A16-1),-10) -> 2.1
... A13836: 1.62 | B13836: 1 | C13836: =IF(B13836=1,10*(A13836-1),-10) -> 6.2

Sheet 1000 parieurs
A1: 1 000 parieurs, 100 paris chacun (F9 = on recommence)
A2: Chaque case tire un pari au hasard dans l'onglet Paris. Colonne CX : le bilan de chaque parieur.
A4: Parieur | B4: 1 | C4: 2 | D4: 3 | E4: 4 | F4: 5 | G4: 6 | H4: 7 | I4: 8 | J4: 9 | K4: 10 | L4: 11 | M4: 12 | N4: 13 | O4: 14 | P4: 15 | Q4: 16 | R4: 17 | S4: 18 | T4: 19 | U4: 20 | V4: 21 | W4: 22 | X4: 23 | Y4: 24 | Z4: 25 | AA4: 26 | AB4: 27 | AC4: 28 | AD4: 29 | AE4: 30 | AF4: 31 | AG4: 32 | AH4: 33 | AI4: 34 | AJ4: 35 | AK4: 36 | AL4: 37 | AM4: 38 | AN4: 39 | AO4: 40 | AP4: 41 | AQ4: 42 | AR4: 43 | AS4: 44 | AT4: 45 | AU4: 46 | AV4: 47 | AW4: 48 | AX4: 49 | AY4: 50 | AZ4: 51 | BA4: 52 | BB4: 53 | BC4: 54 | BD4: 55 | BE4: 56 | BF4: 57 | BG4: 58 | BH4: 59 | BI4: 60 | BJ4: 61 | BK4: 62 | BL4: 63 | BM4: 64 | BN4: 65 | BO4: 66 | BP4: 67 | BQ4: 68 | BR4: 69 | BS4: 70 | BT4: 71 | BU4: 72 | BV4: 73 | BW4: 74 | BX4: 75 | BY4: 76 | BZ4: 77 | CA4: 78 | CB4: 79 | CC4: 80 | CD4: 81 | CE4: 82 | CF4: 83 | CG4: 84 | CH4: 85 | CI4: 86 | CJ4: 87 | CK4: 88 | CL4: 89 | CM4: 90 | CN4: 91 | CO4: 92 | CP4: 93 | CQ4: 94 | CR4: 95 | CS4: 96 | CT4: 97 | CU4: 98 | CV4: 99 | CW4: 100 | CX4: Bilan (€)
A5: 1 | B5: =INDEX(Paris!$C$5:$C$13836,RANDBETWEEN(1,13832)) -> 17.5 | C5: =INDEX(Paris!$C$5:$C$13836,RANDBETWEEN(1,13832)) -> -10 | D5: =INDEX(Paris!$C$5:$C$13836,RANDBETWEEN(1,13832)) -> 2.8 | E5: =INDEX(Paris!$C$5:$C$13836,RANDBETWEEN(1,13832)) -> -10 | F5: =INDEX(Paris!$C$5:$C$13836,RANDBETWEEN(1,13832)) -> -10 | G5: =INDEX(Paris!$C$5:$C$13836,RANDBETWEEN(1,13832)) -> -10 | H5: =INDEX(Paris!$C$5:$C$13836,RANDBETWEEN(1,13832)) -> -10 | I5: =INDEX(Paris!$C$5:$C$13836,RANDBETWEEN(1,13832)) -> -10 | ... CW5: =INDEX(Paris!$C$5:$C$13836,RANDBETWEEN(1,13832)) -> -10 | CX5: =SUM(B5:CW5) -> -43
A6: 2 | B6: =INDEX(Paris!$C$5:$C$13836,RANDBETWEEN(1,13832)) -> 5.9 | C6: =INDEX(Paris!$C$5:$C$13836,RANDBETWEEN(1,13832)) -> 22 | D6: =INDEX(Paris!$C$5:$C$13836,RANDBETWEEN(1,13832)) -> -10 | E6: =INDEX(Paris!$C$5:$C$13836,RANDBETWEEN(1,13832)) -> 38 | F6: =INDEX(Paris!$C$5:$C$13836,RANDBETWEEN(1,13832)) -> 10.5 | G6: =INDEX(Paris!$C$5:$C$13836,RANDBETWEEN(1,13832)) -> -10 | H6: =INDEX(Paris!$C$5:$C$13836,RANDBETWEEN(1,13832)) -> 4.5 | I6: =INDEX(Paris!$C$5:$C$13836,RANDBETWEEN(1,13832)) -> -10 | ... CW6: =INDEX(Paris!$C$5:$C$13836,RANDBETWEEN(1,13832)) -> 5.4 | CX6: =SUM(B6:CW6) -> 77.8
A7: 3 | B7: =INDEX(Paris!$C$5:$C$13836,RANDBETWEEN(1,13832)) -> 3.3 | C7: =INDEX(Paris!$C$5:$C$13836,RANDBETWEEN(1,13832)) -> 3.3 | D7: =INDEX(Paris!$C$5:$C$13836,RANDBETWEEN(1,13832)) -> -10 | E7: =INDEX(Paris!$C$5:$C$13836,RANDBETWEEN(1,13832)) -> -10 | F7: =INDEX(Paris!$C$5:$C$13836,RANDBETWEEN(1,13832)) -> 3.3 | G7: =INDEX(Paris!$C$5:$C$13836,RANDBETWEEN(1,13832)) -> -10 | H7: =INDEX(Paris!$C$5:$C$13836,RANDBETWEEN(1,13832)) -> 15 | I7: =INDEX(Paris!$C$5:$C$13836,RANDBETWEEN(1,13832)) -> 21.5 | ... CW7: =INDEX(Paris!$C$5:$C$13836,RANDBETWEEN(1,13832)) -> -10 | CX7: =SUM(B7:CW7) -> -168.4
A8: 4 | B8: =INDEX(Paris!$C$5:$C$13836,RANDBETWEEN(1,13832)) -> 1.4 | C8: =INDEX(Paris!$C$5:$C$13836,RANDBETWEEN(1,13832)) -> 3.3 | D8: =INDEX(Paris!$C$5:$C$13836,RANDBETWEEN(1,13832)) -> -10 | E8: =INDEX(Paris!$C$5:$C$13836,RANDBETWEEN(1,13832)) -> -10 | F8: =INDEX(Paris!$C$5:$C$13836,RANDBETWEEN(1,13832)) -> -10 | G8: =INDEX(Paris!$C$5:$C$13836,RANDBETWEEN(1,13832)) -> -10 | H8: =INDEX(Paris!$C$5:$C$13836,RANDBETWEEN(1,13832)) -> 6.2 | I8: =INDEX(Paris!$C$5:$C$13836,RANDBETWEEN(1,13832)) -> 9.5 | ... CW8: =INDEX(Paris!$C$5:$C$13836,RANDBETWEEN(1,13832)) -> 6.5 | CX8: =SUM(B8:CW8) -> -194.6
A9: 5 | B9: =INDEX(Paris!$C$5:$C$13836,RANDBETWEEN(1,13832)) -> 2.9 | C9: =INDEX(Paris!$C$5:$C$13836,RANDBETWEEN(1,13832)) -> 2.9 | D9: =INDEX(Paris!$C$5:$C$13836,RANDBETWEEN(1,13832)) -> -10 | E9: =INDEX(Paris!$C$5:$C$13836,RANDBETWEEN(1,13832)) -> 2.8 | F9: =INDEX(Paris!$C$5:$C$13836,RANDBETWEEN(1,13832)) -> 4.3 | G9: =INDEX(Paris!$C$5:$C$13836,RANDBETWEEN(1,13832)) -> -10 | H9: =INDEX(Paris!$C$5:$C$13836,RANDBETWEEN(1,13832)) -> 2.3 | I9: =INDEX(Paris!$C$5:$C$13836,RANDBETWEEN(1,13832)) -> 18 | ... CW9: =INDEX(Paris!$C$5:$C$13836,RANDBETWEEN(1,13832)) -> -10 | CX9: =SUM(B9:CW9) -> 68.7
A10: 6 | B10: =INDEX(Paris!$C$5:$C$13836,RANDBETWEEN(1,13832)) -> 2 | C10: =INDEX(Paris!$C$5:$C$13836,RANDBETWEEN(1,13832)) -> -10 | D10: =INDEX(Paris!$C$5:$C$13836,RANDBETWEEN(1,13832)) -> 3.3 | E10: =INDEX(Paris!$C$5:$C$13836,RANDBETWEEN(1,13832)) -> -10 | F10: =INDEX(Paris!$C$5:$C$13836,RANDBETWEEN(1,13832)) -> -10 | G10: =INDEX(Paris!$C$5:$C$13836,RANDBETWEEN(1,13832)) -> 32 | H10: =INDEX(Paris!$C$5:$C$13836,RANDBETWEEN(1,13832)) -> 2.9 | I10: =INDEX(Paris!$C$5:$C$13836,RANDBETWEEN(1,13832)) -> -10 | ... CW10: =INDEX(Paris!$C$5:$C$13836,RANDBETWEEN(1,13832)) -> 12.8 | CX10: =SUM(B10:CW10) -> 16.3
A11: 7 | B11: =INDEX(Paris!$C$5:$C$13836,RANDBETWEEN(1,13832)) -> -10 | C11: =INDEX(Paris!$C$5:$C$13836,RANDBETWEEN(1,13832)) -> 18.5 | D11: =INDEX(Paris!$C$5:$C$13836,RANDBETWEEN(1,13832)) -> 1.1 | E11: =INDEX(Paris!$C$5:$C$13836,RANDBETWEEN(1,13832)) -> -10 | F11: =INDEX(Paris!$C$5:$C$13836,RANDBETWEEN(1,13832)) -> 16 | G11: =INDEX(Paris!$C$5:$C$13836,RANDBETWEEN(1,13832)) -> -10 | H11: =INDEX(Paris!$C$5:$C$13836,RANDBETWEEN(1,13832)) -> 1.3 | I11: =INDEX(Paris!$C$5:$C$13836,RANDBETWEEN(1,13832)) -> -10 | ... CW11: =INDEX(Paris!$C$5:$C$13836,RANDBETWEEN(1,13832)) -> 4.4 | CX11: =SUM(B11:CW11) -> -89.9
A12: 8 | B12: =INDEX(Paris!$C$5:$C$13836,RANDBETWEEN(1,13832)) -> 1.7 | C12: =INDEX(Paris!$C$5:$C$13836,RANDBETWEEN(1,13832)) -> -10 | D12: =INDEX(Paris!$C$5:$C$13836,RANDBETWEEN(1,13832)) -> -10 | E12: =INDEX(Paris!$C$5:$C$13836,RANDBETWEEN(1,13832)) -> 1.9 | F12: =INDEX(Paris!$C$5:$C$13836,RANDBETWEEN(1,13832)) -> 15 | G12: =INDEX(Paris!$C$5:$C$13836,RANDBETWEEN(1,13832)) -> -10 | H12: =INDEX(Paris!$C$5:$C$13836,RANDBETWEEN(1,13832)) -> 6.1 | I12: =INDEX(Paris!$C$5:$C$13836,RANDBETWEEN(1,13832)) -> 17.5 | ... CW12: =INDEX(Paris!$C$5:$C$13836,RANDBETWEEN(1,13832)) -> -10 | CX12: =SUM(B12:CW12) -> -229.1
A13: 9 | B13: =INDEX(Paris!$C$5:$C$13836,RANDBETWEEN(1,13832)) -> 2.9 | C13: =INDEX(Paris!$C$5:$C$13836,RANDBETWEEN(1,13832)) -> 4.8 | D13: =INDEX(Paris!$C$5:$C$13836,RANDBETWEEN(1,13832)) -> 14.5 | E13: =INDEX(Paris!$C$5:$C$13836,RANDBETWEEN(1,13832)) -> 15 | F13: =INDEX(Paris!$C$5:$C$13836,RANDBETWEEN(1,13832)) -> 20 | G13: =INDEX(Paris!$C$5:$C$13836,RANDBETWEEN(1,13832)) -> -10 | H13: =INDEX(Paris!$C$5:$C$13836,RANDBETWEEN(1,13832)) -> 5.3 | I13: =INDEX(Paris!$C$5:$C$13836,RANDBETWEEN(1,13832)) -> -10 | ... CW13: =INDEX(Paris!$C$5:$C$13836,RANDBETWEEN(1,13832)) -> 14 | CX13: =SUM(B13:CW13) -> 286.5
A14: 10 | B14: =INDEX(Paris!$C$5:$C$13836,RANDBETWEEN(1,13832)) -> 2.2 | C14: =INDEX(Paris!$C$5:$C$13836,RANDBETWEEN(1,13832)) -> 3.3 | D14: =INDEX(Paris!$C$5:$C$13836,RANDBETWEEN(1,13832)) -> -10 | E14: =INDEX(Paris!$C$5:$C$13836,RANDBETWEEN(1,13832)) -> -10 | F14: =INDEX(Paris!$C$5:$C$13836,RANDBETWEEN(1,13832)) -> -10 | G14: =INDEX(Paris!$C$5:$C$13836,RANDBETWEEN(1,13832)) -> -10 | H14: =INDEX(Paris!$C$5:$C$13836,RANDBETWEEN(1,13832)) -> -10 | I14: =INDEX(Paris!$C$5:$C$13836,RANDBETWEEN(1,13832)) -> -10 | ... CW14: =INDEX(Paris!$C$5:$C$13836,RANDBETWEEN(1,13832)) -> -10 | CX14: =SUM(B14:CW14) -> -146.7
A15: 11 | B15: =INDEX(Paris!$C$5:$C$13836,RANDBETWEEN(1,13832)) -> 28 | C15: =INDEX(Paris!$C$5:$C$13836,RANDBETWEEN(1,13832)) -> 17 | D15: =INDEX(Paris!$C$5:$C$13836,RANDBETWEEN(1,13832)) -> -10 | E15: =INDEX(Paris!$C$5:$C$13836,RANDBETWEEN(1,13832)) -> -10 | F15: =INDEX(Paris!$C$5:$C$13836,RANDBETWEEN(1,13832)) -> -10 | G15: =INDEX(Paris!$C$5:$C$13836,RANDBETWEEN(1,13832)) -> 17 | H15: =INDEX(Paris!$C$5:$C$13836,RANDBETWEEN(1,13832)) -> 4.5 | I15: =INDEX(Paris!$C$5:$C$13836,RANDBETWEEN(1,13832)) -> 2.6 | ... CW15: =INDEX(Paris!$C$5:$C$13836,RANDBETWEEN(1,13832)) -> 6.9 | CX15: =SUM(B15:CW15) -> 135.4
A16: 12 | B16: =INDEX(Paris!$C$5:$C$13836,RANDBETWEEN(1,13832)) -> 3.8 | C16: =INDEX(Paris!$C$5:$C$13836,RANDBETWEEN(1,13832)) -> -10 | D16: =INDEX(Paris!$C$5:$C$13836,RANDBETWEEN(1,13832)) -> -10 | E16: =INDEX(Paris!$C$5:$C$13836,RANDBETWEEN(1,13832)) -> -10 | F16: =INDEX(Paris!$C$5:$C$13836,RANDBETWEEN(1,13832)) -> -10 | G16: =INDEX(Paris!$C$5:$C$13836,RANDBETWEEN(1,13832)) -> 14.2 | H16: =INDEX(Paris!$C$5:$C$13836,RANDBETWEEN(1,13832)) -> -10 | I16: =INDEX(Paris!$C$5:$C$13836,RANDBETWEEN(1,13832)) -> -10 | ... CW16: =INDEX(Paris!$C$5:$C$13836,RANDBETWEEN(1,13832)) -> 5.7 | CX16: =SUM(B16:CW16) -> -32.6
... A1004: 1000 | B1004: =INDEX(Paris!$C$5:$C$13836,RANDBETWEEN(1,13832)) -> -10 | C1004: =INDEX(Paris!$C$5:$C$13836,RANDBETWEEN(1,13832)) -> -10 | D1004: =INDEX(Paris!$C$5:$C$13836,RANDBETWEEN(1,13832)) -> 9.5 | E1004: =INDEX(Paris!$C$5:$C$13836,RANDBETWEEN(1,13832)) -> 8.3 | F1004: =INDEX(Paris!$C$5:$C$13836,RANDBETWEEN(1,13832)) -> -10 | G1004: =INDEX(Paris!$C$5:$C$13836,RANDBETWEEN(1,13832)) -> 2.3 | H1004: =INDEX(Paris!$C$5:$C$13836,RANDBETWEEN(1,13832)) -> 5.4 | I1004: =INDEX(Paris!$C$5:$C$13836,RANDBETWEEN(1,13832)) -> 6.7 | ... CW1004: =INDEX(Paris!$C$5:$C$13836,RANDBETWEEN(1,13832)) -> -10 | CX1004: =SUM(B1004:CW1004) -> 60.7

Sheet Distribution
A1: Combien de parieurs finissent gagnants ?
A2: On compte les bilans par tranche de 50 € (NB.SI.ENS).
A4: De (€) | B4: À (€) | C4: Parieurs | D4: Tranche
A5: -600 | B5: -550 | C5: =COUNTIFS('1000 parieurs'!$CX$5:$CX$1004,">="&A5,'1000 parieurs'!$CX$5:$CX$1004,"<"&B5) -> 0 | D5: -600 à -550
A6: -550 | B6: -500 | C6: =COUNTIFS('1000 parieurs'!$CX$5:$CX$1004,">="&A6,'1000 parieurs'!$CX$5:$CX$1004,"<"&B6) -> 0 | D6: -550 à -500
A7: -500 | B7: -450 | C7: =COUNTIFS('1000 parieurs'!$CX$5:$CX$1004,">="&A7,'1000 parieurs'!$CX$5:$CX$1004,"<"&B7) -> 0 | D7: -500 à -450
A8: -450 | B8: -400 | C8: =COUNTIFS('1000 parieurs'!$CX$5:$CX$1004,">="&A8,'1000 parieurs'!$CX$5:$CX$1004,"<"&B8) -> 0 | D8: -450 à -400
A9: -400 | B9: -350 | C9: =COUNTIFS('1000 parieurs'!$CX$5:$CX$1004,">="&A9,'1000 parieurs'!$CX$5:$CX$1004,"<"&B9) -> 0 | D9: -400 à -350
A10: -350 | B10: -300 | C10: =COUNTIFS('1000 parieurs'!$CX$5:$CX$1004,">="&A10,'1000 parieurs'!$CX$5:$CX$1004,"<"&B10) -> 13 | D10: -350 à -300
A11: -300 | B11: -250 | C11: =COUNTIFS('1000 parieurs'!$CX$5:$CX$1004,">="&A11,'1000 parieurs'!$CX$5:$CX$1004,"<"&B11) -> 17 | D11: -300 à -250
A12: -250 | B12: -200 | C12: =COUNTIFS('1000 parieurs'!$CX$5:$CX$1004,">="&A12,'1000 parieurs'!$CX$5:$CX$1004,"<"&B12) -> 45 | D12: -250 à -200
A13: -200 | B13: -150 | C13: =COUNTIFS('1000 parieurs'!$CX$5:$CX$1004,">="&A13,'1000 parieurs'!$CX$5:$CX$1004,"<"&B13) -> 91 | D13: -200 à -150
A14: -150 | B14: -100 | C14: =COUNTIFS('1000 parieurs'!$CX$5:$CX$1004,">="&A14,'1000 parieurs'!$CX$5:$CX$1004,"<"&B14) -> 153 | D14: -150 à -100
A15: -100 | B15: -50 | C15: =COUNTIFS('1000 parieurs'!$CX$5:$CX$1004,">="&A15,'1000 parieurs'!$CX$5:$CX$1004,"<"&B15) -> 177 | D15: -100 à -50
A16: -50 | B16: 0 | C16: =COUNTIFS('1000 parieurs'!$CX$5:$CX$1004,">="&A16,'1000 parieurs'!$CX$5:$CX$1004,"<"&B16) -> 178 | D16: -50 à 0
... A27: 500 | B27: 550 | C27: =COUNTIFS('1000 parieurs'!$CX$5:$CX$1004,">="&A27,'1000 parieurs'!$CX$5:$CX$1004,"<"&B27) -> 0 | D27: 500 à 550
A29: Parieurs gagnants | C29: =COUNTIF('1000 parieurs'!CX5:CX1004,">0")/1000 -> 0.325
A30: Bilan médian (€) | C30: =MEDIAN('1000 parieurs'!CX5:CX1004) -> -48.95
A31: Le plus chanceux (€) | C31: =MAX('1000 parieurs'!CX5:CX1004) -> 341.3

Sheet G6 Distribution
